HinetPy/__init__.py
HinetPy/channel.py
HinetPy/client.py
HinetPy/header.py
HinetPy/utils.py
HinetPy/win32.py
HinetPy-0.10.0.dist-info/LICENSE
HinetPy-0.10.0.dist-info/METADATA
HinetPy-0.10.0.dist-info/WHEEL
HinetPy-0.10.0.dist-info/top_level.txt
HinetPy-0.10.0.dist-info/RECORD
