Metadata-Version: 2.1
Name: HinetPy
Version: 0.10.0
Summary: A Python package for accessing and processing NIED Hi-net seismic data
Author-email: Dongdong Tian <seisman.info@gmail.com>
Project-URL: homepage, https://seisman.github.io/HinetPy/
Project-URL: documentation, https://seisman.github.io/HinetPy/
Project-URL: repository, https://github.com/seisman/HinetPy
Keywords: seismology,NIED,Hi-net,waveform
Classifier: Development Status :: 4 - Beta
Classifier: Intended Audience :: Science/Research
Classifier: Intended Audience :: Education
Classifier: License :: OSI Approved :: MIT License
Classifier: Operating System :: POSIX :: Linux
Classifier: Operating System :: MacOS
Classifier: Programming Language :: Python
Classifier: Programming Language :: Python :: 3.8
Classifier: Programming Language :: Python :: 3.9
Classifier: Programming Language :: Python :: 3.10
Classifier: Programming Language :: Python :: 3.11
Classifier: Programming Language :: Python :: 3.12
Classifier: Programming Language :: Python :: 3 :: Only
Classifier: Topic :: Internet :: WWW/HTTP
Classifier: Topic :: Scientific/Engineering :: Physics
Classifier: Topic :: Utilities
Requires-Python: >=3.8
License-File: LICENSE
Requires-Dist: certifi
Requires-Dist: packaging
Requires-Dist: requests
Requires-Dist: urllib3
